odoo/addons/donation/README.rst
odoo/addons/donation/__init__.py
odoo/addons/donation/__manifest__.py
odoo/addons/donation/post_install.py
odoo/addons/donation/demo/donation_demo.xml
odoo/addons/donation/i18n/donation.pot
odoo/addons/donation/i18n/es.po
odoo/addons/donation/i18n/fr.po
odoo/addons/donation/models/__init__.py
odoo/addons/donation/models/account.py
odoo/addons/donation/models/donation.py
odoo/addons/donation/models/donation_campaign.py
odoo/addons/donation/models/partner.py
odoo/addons/donation/models/users.py
odoo/addons/donation/report/__init__.py
odoo/addons/donation/report/donation_report.py
odoo/addons/donation/report/donation_report_view.xml
odoo/addons/donation/security/donation_security.xml
odoo/addons/donation/security/ir.model.access.csv
odoo/addons/donation/static/description/icon.png
odoo/addons/donation/tests/__init__.py
odoo/addons/donation/tests/test_donation.py
odoo/addons/donation/views/account.xml
odoo/addons/donation/views/donation.xml
odoo/addons/donation/views/donation_campaign.xml
odoo/addons/donation/views/partner.xml
odoo/addons/donation/views/users.xml
odoo/addons/donation/wizard/__init__.py
odoo/addons/donation/wizard/donation_validate.py
odoo/addons/donation/wizard/donation_validate_view.xml
odoo/addons/donation/wizard/tax_receipt_option_switch.py
odoo/addons/donation/wizard/tax_receipt_option_switch_view.xml
odoo11_addon_donation-11.0.1.0.0.dist-info/METADATA
odoo11_addon_donation-11.0.1.0.0.dist-info/RECORD
odoo11_addon_donation-11.0.1.0.0.dist-info/WHEEL
odoo11_addon_donation-11.0.1.0.0.dist-info/top_level.txt
